helloworld.py
helloworld_rrodorr-0.0.1.dist-info/METADATA
helloworld_rrodorr-0.0.1.dist-info/WHEEL
helloworld_rrodorr-0.0.1.dist-info/top_level.txt
helloworld_rrodorr-0.0.1.dist-info/RECORD
